Metadata-Version: 2.1
Name: example-pkg-AndyPythonCodes
Version: 0.0.4
Summary: send pdf to server
Home-page: https://github.com/AndyPythonCode/Cliente-Servidor
Author: Andy Arciniega
Author-email: servidorandycode@gmail.com
License: UNKNOWN
Platform: UNKNOWN
Classifier: Programming Language :: Python :: 3
Classifier: License :: OSI Approved :: MIT License
Classifier: Operating System :: OS Independent
Requires-Python: >=3.8
Requires-Dist: django (>=3.1.3)
